biostats/__init__.py
biostats/__main__.py
biostats/app.py
biostats/azure.tcl
biostats/data.py
biostats/help.py
biostats/master.py
biostats/plot.py
biostats/test.py
biostats/widget.py
biostats/datasets/__init__.py
biostats/datasets/binomial_test.csv
biostats/datasets/categorical.csv
biostats/datasets/chi_square_test.csv
biostats/datasets/chi_square_test_fit.csv
biostats/datasets/contingency.csv
biostats/datasets/correlation.csv
biostats/datasets/correlation_matrix.csv
biostats/datasets/epidemiologic_study.csv
biostats/datasets/factor_analysis.csv
biostats/datasets/fisher_exact_test.csv
biostats/datasets/flights.csv
biostats/datasets/friedman_test.csv
biostats/datasets/iris.csv
biostats/datasets/kruskal_wallis_test.csv
biostats/datasets/linear_discriminant_analysis.csv
biostats/datasets/mantel_haenszel_test.csv
biostats/datasets/mcnemar_exact_test.csv
biostats/datasets/mcnemar_test.csv
biostats/datasets/median_test.csv
biostats/datasets/multinomial_logistic_regression.csv
biostats/datasets/multiple_linear_regression.csv
biostats/datasets/multiple_logistic_regression.csv
biostats/datasets/multivariate_anova.csv
biostats/datasets/numeral.csv
biostats/datasets/numeral_grouped.csv
biostats/datasets/one_sample_t_test.csv
biostats/datasets/one_way_ancova.csv
biostats/datasets/one_way_anova.csv
biostats/datasets/ordered_logistic_regression.csv
biostats/datasets/paired_t_test.csv
biostats/datasets/pairwise_t_test.csv
biostats/datasets/penguins.csv
biostats/datasets/principal_component_analysis.csv
biostats/datasets/repeated_measures_anova.csv
biostats/datasets/screening_test.csv
biostats/datasets/sign_test.csv
biostats/datasets/simple_linear_regression.csv
biostats/datasets/simple_logistic_regression.csv
biostats/datasets/spearman_rank_correlation.csv
biostats/datasets/tips.csv
biostats/datasets/titanic.csv
biostats/datasets/two_sample_t_test.csv
biostats/datasets/two_way_ancova.csv
biostats/datasets/two_way_anova.csv
biostats/datasets/wilcoxon_rank_sum_test.csv
biostatistics-0.0.1.dist-info/LICENSE
biostatistics-0.0.1.dist-info/METADATA
biostatistics-0.0.1.dist-info/WHEEL
biostatistics-0.0.1.dist-info/entry_points.txt
biostatistics-0.0.1.dist-info/top_level.txt
biostatistics-0.0.1.dist-info/RECORD
