Metadata-Version: 2.1
Name: biostatistics
Version: 0.0.1
Summary: Statistical software with intuitive interfaces and comprehensive functions
Home-page: https://github.com/hikarimusic/BIOSTATS
Author: Yeu-Guang Tung
Author-email: hikarimusic.tm@gmail.com
License: MIT
Project-URL: Documentation, https://hikarimusic.github.io/BIOSTATS
Project-URL: Source Code, https://github.com/hikarimusic/BIOSTATS
Classifier: License :: OSI Approved :: MIT License
Classifier: Topic :: Scientific/Engineering
Classifier: Intended Audience :: Science/Research
Classifier: Programming Language :: Python :: 3.7
Classifier: Programming Language :: Python :: 3.8
Classifier: Programming Language :: Python :: 3.9
Classifier: Programming Language :: Python :: 3.10
License-File: LICENSE
Requires-Dist: factor-analyzer
Requires-Dist: matplotlib
Requires-Dist: numpy
Requires-Dist: openpyxl
Requires-Dist: pandas
Requires-Dist: pyreadstat
Requires-Dist: scikit-learn
Requires-Dist: scipy
Requires-Dist: seaborn
Requires-Dist: statsmodels
Requires-Dist: tabulate
